coldp/__init__.py
coldp/coldp.py
coldp/coldp_add.py
coldp/coldp_distribution.py
coldp/testit.py
coldp-2025.4.3.dist-info/METADATA
coldp-2025.4.3.dist-info/WHEEL
coldp-2025.4.3.dist-info/licenses/LICENSE
coldp-2025.4.3.dist-info/RECORD
