Metadata-Version: 2.4
Name: coldp
Version: 2025.4.3
Summary: Python tools for working with taxonomic checklists organised as Catalogue of Life Data Package (COLDP) format
Project-URL: Homepage, https://github.com/dhobern/py-coldp
Project-URL: Issues, https://github.com/dhobern/py-coldp/issues
Author-email: Donald Hobern <dhobern@gmail.com>
License: MIT License
License-File: LICENSE
Keywords: COLDP,Catalogue of Life,taxonomic checklist
Classifier: Development Status :: 4 - Beta
Classifier: License :: OSI Approved :: MIT License
Classifier: Operating System :: OS Independent
Classifier: Programming Language :: Python :: 3
Requires-Python: >=3.8
Requires-Dist: numpy
Requires-Dist: pandas
Provides-Extra: doc
Requires-Dist: sphinx; extra == 'doc'
Requires-Dist: sphinx-paramlinks; extra == 'doc'
Provides-Extra: test
Requires-Dist: pytest; extra == 'test'
